plutus_terminal/__init__.py
plutus_terminal/core/__init__.py
plutus_terminal/core/config.py
plutus_terminal/core/db/__init__.py
plutus_terminal/core/db/models.py
plutus_terminal/core/exceptions.py
plutus_terminal/core/exchange/__init__.py
plutus_terminal/core/exchange/base.py
plutus_terminal/core/exchange/foxify/__init__.py
plutus_terminal/core/exchange/foxify/abi/foxify_funded_factory.json
plutus_terminal/core/exchange/foxify/abi/foxify_funded_trader.json
plutus_terminal/core/exchange/foxify/abi/foxify_order_book.json
plutus_terminal/core/exchange/foxify/abi/foxify_position_router.json
plutus_terminal/core/exchange/foxify/abi/foxify_referral_storage.json
plutus_terminal/core/exchange/foxify/abi/foxify_router.json
plutus_terminal/core/exchange/foxify/abi/foxify_time_lock.json
plutus_terminal/core/exchange/foxify/abi/foxify_vault.json
plutus_terminal/core/exchange/foxify/abi/usdc.json
plutus_terminal/core/exchange/foxify/exchange.py
plutus_terminal/core/exchange/foxify/fetcher.py
plutus_terminal/core/exchange/foxify/funded_exchange.py
plutus_terminal/core/exchange/foxify/funded_fetcher.py
plutus_terminal/core/exchange/foxify/funded_trader.py
plutus_terminal/core/exchange/foxify/options.py
plutus_terminal/core/exchange/foxify/pair_map.json
plutus_terminal/core/exchange/foxify/trader.py
plutus_terminal/core/exchange/foxify/utils.py
plutus_terminal/core/exchange/helpers.py
plutus_terminal/core/exchange/types.py
plutus_terminal/core/exchange/valid_exchanges.py
plutus_terminal/core/exchange/web3/__init__.py
plutus_terminal/core/exchange/web3/abi/usdc.json
plutus_terminal/core/exchange/web3/cycle_provider.py
plutus_terminal/core/exchange/web3/pyth_feed_id.json
plutus_terminal/core/exchange/web3/web3_utils.py
plutus_terminal/core/news/__init__.py
plutus_terminal/core/news/base.py
plutus_terminal/core/news/filter/__init__.py
plutus_terminal/core/news/filter/_actions.py
plutus_terminal/core/news/filter/_filters.py
plutus_terminal/core/news/filter/filter_manager.py
plutus_terminal-0.1.0b18.dist-info/LICENSE
plutus_terminal-0.1.0b18.dist-info/METADATA
plutus_terminal-0.1.0b18.dist-info/WHEEL
plutus_terminal-0.1.0b18.dist-info/entry_points.txt
plutus_terminal-0.1.0b18.dist-info/RECORD
